drone/__init__.py
drone/api.py
drone/config.py
drone/decorators.py
drone/drone.py
drone/http.py
drone/users.py
drone_python-1.0.0.dist-info/LICENSE
drone_python-1.0.0.dist-info/METADATA
drone_python-1.0.0.dist-info/WHEEL
drone_python-1.0.0.dist-info/top_level.txt
drone_python-1.0.0.dist-info/RECORD
