Metadata-Version: 2.1
Name: drone-python
Version: 1.0.0
Summary: Python client for the Drone CI public API
Home-page: https://github.com/tinvaan/pydroneio
Author: Harish Navnit
Author-email: harishnavnit@gmail.com
License: UNKNOWN
Platform: UNKNOWN
Requires-Python: >3.6
Requires-Dist: requests (==2.24.0)
